earnest/__init__.py
earnest/airflow_plugin/__init__.py
earnest/airflow_plugin/operators/__init__.py
earnest/airflow_plugin/operators/great_expectations_kubernetes_pod_operator.py
earnest/airflow_plugin/operators/kubernetes_pod_operator.py
earnest_airflow_plugin-0.0.1.dist-info/LICENSE
earnest_airflow_plugin-0.0.1.dist-info/METADATA
earnest_airflow_plugin-0.0.1.dist-info/WHEEL
earnest_airflow_plugin-0.0.1.dist-info/top_level.txt
earnest_airflow_plugin-0.0.1.dist-info/RECORD
