Metadata-Version: 2.1
Name: earnest-airflow-plugin
Version: 0.0.1
Summary: Operators and Hooks for Airflow
Home-page: https://github.com/EarnestResearch/airflow-plugin
Author: Earnest Research
Author-email: python-package-index@earnestresearch.com 
License: MIT License
Project-URL: Source, https://github.com/EarnestResearch/airflow-plugin
Keywords: airflow,plugin
Platform: UNKNOWN
Requires-Python: >=3.5
Requires-Dist: apache-airflow[kubernetes] (==1.10.10)
